mighty_patcher/__init__.py
mighty_patcher/_better_mocking.c
mighty_patcher/_better_mocking.cpython-36m-darwin.so
mighty_patcher/pytest.py
mighty_patcher/reload.py
mighty_patcher/replacement.py
mighty_patcher/watch.py
mighty_patcher-0.1.dist-info/AUTHORS.rst
mighty_patcher-0.1.dist-info/LICENSE
mighty_patcher-0.1.dist-info/METADATA
mighty_patcher-0.1.dist-info/WHEEL
mighty_patcher-0.1.dist-info/entry_points.txt
mighty_patcher-0.1.dist-info/top_level.txt
mighty_patcher-0.1.dist-info/RECORD
