Metadata-Version: 2.1
Name: mighty-patcher
Version: 0.1
Summary: The restart-less hot-reloading wonder, Mighty Patcher
Home-page: https://github.com/rtpg/mighty_patcher
Author: Raphael Gaschignard
Author-email: raphael@rtpg.co
License: BSD 3-Clause License
Project-URL: Issue Tracker, https://github.com/rtpg/mighty_patcher/issues
Keywords: debugging
Platform: UNKNOWN
Classifier: Development Status :: 3 - Alpha
Classifier: Intended Audience :: Developers
Classifier: License :: OSI Approved :: BSD License
Classifier: Operating System :: Unix
Classifier: Operating System :: POSIX
Classifier: Operating System :: Microsoft :: Windows
Classifier: Programming Language :: Python
Classifier: Programming Language :: Python :: 3.7
Classifier: Programming Language :: Python :: Implementation :: CPython
Classifier: Topic :: Utilities
Requires-Python: !=3.0.*, !=3.1.*, !=3.2.*, !=3.3.*
Requires-Dist: watchdog
